simplepki/__init__.py
simplepki/simplepki.py
simplepki-0.0.6.dist-info/LICENSE
simplepki-0.0.6.dist-info/METADATA
simplepki-0.0.6.dist-info/WHEEL
simplepki-0.0.6.dist-info/entry_points.txt
simplepki-0.0.6.dist-info/top_level.txt
simplepki-0.0.6.dist-info/RECORD
