Metadata-Version: 2.1
Name: simplepki
Version: 0.0.6
Summary: A simple CLI for making a pki
Home-page: https://gitlab.com/digitalarc/simplepki
Author: Jove Dahle
License: MIT
Keywords: simple pki tools
Platform: UNKNOWN
Classifier: Development Status :: 2 - Pre-Alpha
Classifier: Environment :: Console
Classifier: Programming Language :: Python :: 3
Classifier: License :: OSI Approved :: MIT License
Requires-Python: >=3.6
Requires-Dist: cryptography (>=2.8)
Requires-Dist: click (>=7.1.1)
Requires-Dist: questionary (>=1.5.1)
